nornir_pyntc/__init__.py
nornir_pyntc/connections/__init__.py
nornir_pyntc/connections/pyntc_connection.py
nornir_pyntc/py.typed
nornir_pyntc/tasks/__init__.py
nornir_pyntc/tasks/pyntc_config.py
nornir_pyntc/tasks/pyntc_file_copy.py
nornir_pyntc/tasks/pyntc_install_os.py
nornir_pyntc/tasks/pyntc_reboot.py
nornir_pyntc/tasks/pyntc_save.py
nornir_pyntc/tasks/pyntc_show.py
nornir_pyntc-3.0.0.dist-info/LICENSE
nornir_pyntc-3.0.0.dist-info/METADATA
nornir_pyntc-3.0.0.dist-info/WHEEL
nornir_pyntc-3.0.0.dist-info/entry_points.txt
nornir_pyntc-3.0.0.dist-info/RECORD
