Metadata-Version: 2.1
Name: nornir-pyntc
Version: 3.0.0
Summary: pyntc plugin for Nornir
Home-page: https://github.com/networktocode-llc/nornir_pyntc
License: Apache-2.0
Author: Network to Code, LLC
Author-email: info@networktocode.com
Requires-Python: >=3.8,<4.0
Classifier: License :: OSI Approved :: Apache Software License
Classifier: Programming Language :: Python :: 3
Classifier: Programming Language :: Python :: 3.8
Classifier: Programming Language :: Python :: 3.9
Classifier: Programming Language :: Python :: 3.10
Classifier: Programming Language :: Python :: 3.11
Classifier: Programming Language :: Python :: 3.12
Requires-Dist: nornir (>=3.2.0,<4.0.0)
Requires-Dist: pyntc (>=2.0.0,<3.0.0)
Project-URL: Repository, https://github.com/networktocode-llc/nornir_pyntc
